serpy/__init__.py
serpy_rest-0.1.1.dist-info/METADATA
serpy_rest-0.1.1.dist-info/WHEEL
serpy_rest-0.1.1.dist-info/top_level.txt
serpy_rest-0.1.1.dist-info/RECORD
