Metadata-Version: 2.4
Name: serpy-rest
Version: 0.1.1
Summary: A minimal ASGI web framework for Python.
Home-page: https://github.com/ragav2005/SerPy
Author: Ragav Vignes
Author-email: ragavvignesviswanathan@gmail.com
Classifier: Programming Language :: Python :: 3
Classifier: License :: OSI Approved :: MIT License
Classifier: Operating System :: OS Independent
Classifier: Framework :: AsyncIO
Requires-Python: >=3.7
Requires-Dist: uvicorn
Dynamic: author
Dynamic: author-email
Dynamic: classifier
Dynamic: description
Dynamic: description-content-type
Dynamic: home-page
Dynamic: requires-dist
Dynamic: requires-python
Dynamic: summary
